bdm2/__init__.py
bdm2/constants/__init__.py
bdm2/constants/global_setup/__init__.py
bdm2/constants/global_setup/bats.py
bdm2/constants/global_setup/data.py
bdm2/constants/global_setup/data_columns.py
bdm2/constants/global_setup/encoders.py
bdm2/constants/global_setup/engine.py
bdm2/constants/global_setup/env.py
bdm2/constants/global_setup/group_by.py
bdm2/constants/global_setup/main_config_old.py
bdm2/constants/global_setup/server_paths.py
bdm2/constants/patterns/__init__.py
bdm2/constants/patterns/regexp_patterns.py
bdm2/data_handling/__init__.py
bdm2/data_handling/dataset/__init__.py
bdm2/data_handling/dataset/collect_and_prepare_data.py
bdm2/data_handling/dataset/components/__init__.py
bdm2/data_handling/dataset/components/api_dataset_queries.py
bdm2/data_handling/dataset/components/dataset_params.py
bdm2/data_handling/dataset/components/dataset_queries.py
bdm2/data_handling/dataset/components/set_actual_mass.py
bdm2/data_handling/dataset/default_dataset_collector.py
bdm2/data_handling/dataset/mahalanobis/__init__.py
bdm2/data_handling/dataset/mahalanobis/components/__init__.py
bdm2/data_handling/dataset/mahalanobis/components/check.py
bdm2/data_handling/dataset/mahalanobis/components/distance_check.py
bdm2/data_handling/dataset/mahalanobis/components/methods.py
bdm2/data_handling/dataset/mahalanobis/components/params.py
bdm2/data_handling/dataset/mahalanobis/run_mahalanobis.py
bdm2/data_handling/dataset/train/__init__.py
bdm2/data_handling/dataset/train/get_train_datasets.py
bdm2/data_handling/generated_data/__init__.py
bdm2/data_handling/generated_data/checks/__init__.py
bdm2/data_handling/generated_data/checks/interpolation_outliers_search/components/calculations.py
bdm2/data_handling/generated_data/checks/interpolation_outliers_search/components/common.py
bdm2/data_handling/generated_data/checks/interpolation_outliers_search/components/plots.py
bdm2/data_handling/generated_data/checks/interpolation_outliers_search/components/target_weights.py
bdm2-0.2.1.dist-info/METADATA
bdm2-0.2.1.dist-info/WHEEL
bdm2-0.2.1.dist-info/RECORD
