Metadata-Version: 2.1
Name: bdm2
Version: 0.2.1
Summary: 
Author: Anastasia Pshichenko
Author-email: avp@pawlin.ru
Requires-Python: >=3.9,<3.12
Classifier: Programming Language :: Python :: 3
Classifier: Programming Language :: Python :: 3.9
Classifier: Programming Language :: Python :: 3.10
Classifier: Programming Language :: Python :: 3.11
Requires-Dist: brddb (==0.0.19)
Requires-Dist: clickhouse-connect (>=0.7.16,<0.8.0)
Requires-Dist: gitpython (>=3.1.43,<4.0.0)
Requires-Dist: hyperpyyaml (>=1.2.2,<2.0.0)
Requires-Dist: loguru (>=0.7.2,<0.8.0)
Requires-Dist: numpy (==1.23.5)
Requires-Dist: openpyxl (>=3.1.4,<4.0.0)
Requires-Dist: pandas (==1.5.3)
Requires-Dist: psycopg2-binary (>=2.9,<3.0)
Requires-Dist: pydantic-settings (>=2.5.2,<3.0.0)
Requires-Dist: python-dotenv (>=1.0.1,<2.0.0)
Requires-Dist: pytz (>=2024.1,<2025.0)
Requires-Dist: pyyaml (>=6.0.1,<7.0.0)
Requires-Dist: scikit-learn (>=1.5.2,<2.0.0)
Requires-Dist: scp (>=0.14.5,<0.15.0)
Requires-Dist: sqlalchemy (>=2.0.30,<3.0.0)
Requires-Dist: tqdm (>=4.66.4,<5.0.0)
Requires-Dist: urllib3 (==1.26.19)
